somepytools/__init__.py
somepytools/colab_tools.py
somepytools/constants.py
somepytools/general.py
somepytools/image.py
somepytools/io.py
somepytools/torch.py
somepytools/typing.py
somepytools/video.py
somepytools-1.4.0.dist-info/LICENSE
somepytools-1.4.0.dist-info/METADATA
somepytools-1.4.0.dist-info/WHEEL
somepytools-1.4.0.dist-info/RECORD
