Metadata-Version: 2.3
Name: somepytools
Version: 1.4.0
Summary: Just some useful Python tools
License: Apache-2.0
Keywords: tools,utilities,python,torch,opencv
Author: Vladilav Goncharenko
Author-email: vladislav.goncharenko@phystech.edu
Maintainer: Vladislav Goncharenko
Maintainer-email: vladislav.goncharenko@phystech.edu
Requires-Python: >=3.9
Classifier: License :: OSI Approved :: Apache Software License
Classifier: Programming Language :: Python :: 3
Classifier: Programming Language :: Python :: 3.9
Classifier: Programming Language :: Python :: 3.10
Classifier: Programming Language :: Python :: 3.11
Classifier: Programming Language :: Python :: 3.12
Classifier: Programming Language :: Python :: 3.13
Provides-Extra: all
Requires-Dist: PyYAML (>=6.0,<7.0) ; extra == "all"
Requires-Dist: matplotlib (>=3.5.1,<4.0.0) ; extra == "all"
Requires-Dist: numpy (>=1.22.3,<2.0.0) ; extra == "all"
Requires-Dist: opencv-python-headless (>=4.5.5,<5.0.0) ; extra == "all"
Requires-Dist: toml (>=0.10.2,<0.11.0) ; extra == "all"
Requires-Dist: torch (>=1.11.0,<2.0.0) ; extra == "all"
Project-URL: Repository, https://github.com/v-goncharenko/somepytools
